pdf_section_parser/__init__.py
pdf_section_parser/config.py
pdf_section_parser/parser.py
pdf_section_parser/utils/__init__.py
pdf_section_parser/utils/boundaries.py
pdf_section_parser/utils/pdf.py
pdf_section_parser/utils/text.py
pdf_section_parser/utils/visualization.py
spanish_pdf_parser-0.1.0.dist-info/LICENSE
spanish_pdf_parser-0.1.0.dist-info/METADATA
spanish_pdf_parser-0.1.0.dist-info/WHEEL
spanish_pdf_parser-0.1.0.dist-info/top_level.txt
spanish_pdf_parser-0.1.0.dist-info/RECORD
