Metadata-Version: 2.2
Name: spanish_pdf_parser
Version: 0.1.0
Summary: A Python package for processing PDFs with header and footer detection
Author: Tamara Orlich
Author-email: Tamara Orlich <tamara.orlich@borah.agency>
License: spanish-pdf-parser
Project-URL: Homepage, https://github.com/BorahLabs/spanish_pdf_parser
Project-URL: Repository, https://github.com/BorahLabs/spanish_pdf_parser
Project-URL: Documentation, https://github.com/BorahLabs/spanish_pdf_parser#readme
Keywords: pdf,parser,spanish,text-extraction,document-processing
Requires-Python: >=3.8
License-File: LICENSE
Requires-Dist: pymupdf>=1.24.0
Requires-Dist: pymupdf4llm>=0.0.17
Requires-Dist: tqdm>=4.65.0
Dynamic: author
Dynamic: requires-python
